green_cli/__init__.py
green_cli/btc.py
green_cli/common.py
green_cli/context.py
green_cli/decorators.py
green_cli/gdk_resolve.py
green_cli/green.py
green_cli/green_cli.py
green_cli/liquid.py
green_cli/notifications.py
green_cli/param_types.py
green_cli/session.py
green_cli/twofa.py
green_cli/tx.py
green_cli/utils.py
green_cli/authenticators/__init__.py
green_cli/authenticators/default.py
green_cli/authenticators/hardware.py
green_cli/authenticators/jade.py
green_cli/authenticators/wally.py
green_cli/authenticators/watchonly.py
green_cli-0.8.1.dist-info/METADATA
green_cli-0.8.1.dist-info/WHEEL
green_cli-0.8.1.dist-info/entry_points.txt
green_cli-0.8.1.dist-info/top_level.txt
green_cli-0.8.1.dist-info/RECORD
