Metadata-Version: 2.4
Name: green_cli
Version: 0.8.1
Summary: Blockstream Green Command Line Interface
Home-page: https://github.com/Blockstream/green_cli
Author: Blockstream
Author-email: inquiries@blockstream.com
License: MIT
Project-URL: Documentation, https://github.com/Blockstream/green_cli/README.md
Project-URL: Source, https://github.com/Blockstream/green_cli
Project-URL: Tracker, https://github.com/Blockstream/green_cli/issues
Keywords: Blockstream,Green,Bitcoin,wallet,Liquid,Elements,BTC
Classifier: Development Status :: 3 - Alpha
Classifier: Environment :: Console
Classifier: Intended Audience :: Developers
Classifier: Topic :: Software Development
Classifier: License :: OSI Approved :: MIT License
Classifier: Programming Language :: Python :: 3
Requires-Dist: wallycore>=1.4.0
Requires-Dist: green_gdk>=0.75.0
Requires-Dist: click>=8.1.7
Requires-Dist: click-repl>=0.3.0
Provides-Extra: jade
Requires-Dist: jade_client>=1.0.32; extra == "jade"
Dynamic: author
Dynamic: author-email
Dynamic: classifier
Dynamic: description
Dynamic: home-page
Dynamic: keywords
Dynamic: license
Dynamic: project-url
Dynamic: provides-extra
Dynamic: requires-dist
Dynamic: summary
